ishikawa/__init__
ishikawa/diagram.py
ishikawa-0.0.5.dist-info/METADATA
ishikawa-0.0.5.dist-info/WHEEL
ishikawa-0.0.5.dist-info/licenses/LICENSE
ishikawa-0.0.5.dist-info/RECORD
