Metadata-Version: 2.4
Name: ishikawa
Version: 0.0.5
Summary: Ishikawa is a library used to draw a fish (also known as ishikawa) diagram
Project-URL: Homepage, https://github.com/kaikerochaalves/Ishikawa.git
Project-URL: Issues, https://github.com/kaikerochaalves/Ishikawa.git
Author-email: Kaike Sa Teles Rocha Alves <kaikerochaalves@outlook.com>
License-File: LICENSE
Classifier: License :: OSI Approved :: GNU General Public License v3 (GPLv3)
Classifier: Programming Language :: Python :: 3
Requires-Python: >=3.0
Requires-Dist: matplotlib
